Workbook

Sheet 📋 Instructions
A1: 🏆 GAS 2026 HACKATHON JUDGING WORKBOOK
A3: HOW TO USE THIS WORKBOOK
A5: STEP 1: Each Judge Uses Their Own Sheet
A6: • Byron scores on the "Byron" sheet
A7: • Karthik scores on the "Karthik" sheet
A8: • Molly scores on the "Molly" sheet
A9: • Jamie scores on the "Jamie" sheet
A11: STEP 2: Score Each Team 1-10 on Each Criterion
A12: • 1-2 = Needs Development — major gaps or missing elements
A13: • 3-4 = Emerging — partial attempt with room for growth
A14: • 5-6 = Solid Foundation — meets core requirements with potential to build on
A15: • 7-8 = Strong — well-executed solution that goes beyond basics
... A52: 💡 Tip: Use half-points (e.g., 6.5) when a team falls between levels.

Sheet Byron
A1: 🏆 GAS 2026 HACKATHON - BYRON CLYMER
A2: Score each criterion 1-10 (10 = Excellent). Weighted Total auto-calculates.
A3: WEIGHTAGE → | C3: 10% | D3: 25% | E3: 30% | F3: 25% | G3: 10%
A4: # | B4: Team | C4: Problem (10%) | D4: Innovation (25%) | E4: Technical (30%) | F4: Business (25%) | G4: Presentation (10%) | H4: Weighted Total | I4: Quick Notes
A5: 1 | B5: Lockton Govern-Lens | C5: 9 | D5: 5 | E5: 5 | F5: 6 | G5: 5 | H5: =IF(COUNTA(C5:G5)=5,(0.1*C5+0.25*D5+0.3*E5+0.25*F5+0.1*G5),"") -> 5.65
A6: 2 | B6: Lockton Tech Squad | C6: 9 | D6: 5 | E6: 5 | F6: 6 | G6: 6 | H6: =IF(COUNTA(C6:G6)=5,(0.1*C6+0.25*D6+0.3*E6+0.25*F6+0.1*G6),"") -> 5.75 | I6: When reading goes too fast
A7: 3 | B7: The Sentinels | C7: 9 | D7: 7 | E7: 6 | F7: 7 | G7: 6 | H7: =IF(COUNTA(C7:G7)=5,(0.1*C7+0.25*D7+0.3*E7+0.25*F7+0.1*G7),"") -> 6.8
A8: 4 | B8: Lockathon | C8: 9 | D8: 6 | E8: 7 | F8: 6 | G8: 5 | H8: =IF(COUNTA(C8:G8)=5,(0.1*C8+0.25*D8+0.3*E8+0.25*F8+0.1*G8),"") -> 6.5
A9: 5 | B9: Neural Ninjas | C9: 9 | D9: 5 | E9: 6 | F9: 6 | G9: 6 | H9: =IF(COUNTA(C9:G9)=5,(0.1*C9+0.25*D9+0.3*E9+0.25*F9+0.1*G9),"") -> 6.05 | I9: need emp id
A10: 6 | B10: Jnana Flux | C10: 9 | D10: 6 | E10: 7 | F10: 7 | G10: 6 | H10: =IF(COUNTA(C10:G10)=5,(0.1*C10+0.25*D10+0.3*E10+0.25*F10+0.1*G10),"") -> 6.85 | I10: 2 entry pts, like Teams interface
A11: 7 | B11: Locktonauts | C11: 9 | D11: 6 | E11: 7 | F11: 7 | G11: 7 | H11: =IF(COUNTA(C11:G11)=5,(0.1*C11+0.25*D11+0.3*E11+0.25*F11+0.1*G11),"") -> 6.95 | I11: add client payment and do a demo for Account
A12: 8 | B12: Lockton AIvengers | C12: 9 | D12: 7 | E12: 6 | F12: 7 | G12: 5 | H12: =IF(COUNTA(C12:G12)=5,(0.1*C12+0.25*D12+0.3*E12+0.25*F12+0.1*G12),"") -> 6.7 | I12: market themes
A13: 9 | B13: Hack & LOCK | C13: 9 | D13: 7 | E13: 6 | F13: 7 | G13: 6 | H13: =IF(COUNTA(C13:G13)=5,(0.1*C13+0.25*D13+0.3*E13+0.25*F13+0.1*G13),"") -> 6.8
A14: 10 | B14: PO 360 | C14: 9 | D14: 6 | E14: 7 | F14: 7 | G14: 7 | H14: =IF(COUNTA(C14:G14)=5,(0.1*C14+0.25*D14+0.3*E14+0.25*F14+0.1*G14),"") -> 6.95 | I14: email interface, invoice processing
A15: 11 | B15: Lockton Legends | C15: 9 | D15: 6 | E15: 7 | F15: 8 | G15: 8 | H15: =IF(COUNTA(C15:G15)=5,(0.1*C15+0.25*D15+0.3*E15+0.25*F15+0.1*G15),"") -> 7.3
A16: 12 | B16: Ticket Hunters | C16: 9 | D16: 6 | E16: 7 | F16: 7 | G16: 7 | H16: =IF(COUNTA(C16:G16)=5,(0.1*C16+0.25*D16+0.3*E16+0.25*F16+0.1*G16),"") -> 6.95 | I16: has revnewl info
A17: 13 | B17: CloudMesh | C17: 9 | D17: 6 | E17: 6 | F17: 6 | G17: 7 | H17: =IF(COUNTA(C17:G17)=5,(0.1*C17+0.25*D17+0.3*E17+0.25*F17+0.1*G17),"") -> 6.4

Sheet Karthik
A1: 🏆 GAS 2026 HACKATHON - KARTHIK RAMADOSS
A2: Score each criterion 1-10 (10 = Excellent). Weighted Total auto-calculates.
A3: WEIGHTAGE → | C3: 10% | D3: 25% | E3: 30% | F3: 25% | G3: 10%
A4: # | B4: Team | C4: Problem (10%) | D4: Innovation (25%) | E4: Technical (30%) | F4: Business (25%) | G4: Presentation (10%) | H4: Weighted Total | I4: Quick Notes
A5: 1 | B5: Lockton Govern-Lens | C5: 6 | D5: 7 | E5: 7 | F5: 8 | G5: 8 | H5: =IF(COUNTA(C5:G5)=5,(0.1*C5+0.25*D5+0.3*E5+0.25*F5+0.1*G5),"") -> 7.25 | I5: Adhiraj P - IT Budget management. Chatbot. PowerBi dashboard. AI agent -> stakeholders Forecasting agent. Future: get forecast recommendation.
A6: 2 | B6: Lockton Tech Squad | C6: 6 | D6: 6 | E6: 9 | F6: 8 | G6: 9 | H6: =IF(COUNTA(C6:G6)=5,(0.1*C6+0.25*D6+0.3*E6+0.25*F6+0.1*G6),"") -> 7.7 | I6: People Hub: Amal, Puru, Sathish, Divya, Bharathi, Hema. Associate Directory- Unified AI powered associate experience for Lockton. Detailed panel. Multiple custom views. (editable information). Tams app - agent driven for people lookup. Web assistant. Data design - combining all the data. Graph API, Guthub Copilot, Copilot Studio - multi view
A7: 3 | B7: The Sentinels | C7: 6 | D7: 7 | E7: 7 | F7: 8 | G7: 8 | H7: =IF(COUNTA(C7:G7)=5,(0.1*C7+0.25*D7+0.3*E7+0.25*F7+0.1*G7),"") -> 7.25 | I7: Invoice use case: Vidyadharan, Raveendran, Aishwarya, Ravikumar, Ramesh, Krishanan: Business value. PowerBI report. Sharepoint list backend. Full automated workflow. ApprovalFlow - FLOW.
A8: 4 | B8: Lockathon | C8: 6 | D8: 7 | E8: 7 | F8: 8 | G8: 10 | H8: =IF(COUNTA(C8:G8)=5,(0.1*C8+0.25*D8+0.3*E8+0.25*F8+0.1*G8),"") -> 7.45 | I8: Amaldev - IT budget forecasting. Litty - Copilot studio - GPT5 reasoning. Proactive prompts. Sharepoint web chat. PowerBI link. AI extraction.
A9: 5 | B9: Neural Ninjas | C9: 7 | D9: 6 | E9: 6 | F9: 6 | G9: 8 | H9: =IF(COUNTA(C9:G9)=5,(0.1*C9+0.25*D9+0.3*E9+0.25*F9+0.1*G9),"") -> 6.3 | I9: Associate Rolodex: Stephen. (Sarath, Ancy,Sajith, Sejin, Sreya). Ninjas. Teams - thought about adoption. Manager or executive level. Multi application access view - could be powerful - EMP 360. Creating a new database to create a combined view of associates.
A10: 6 | B10: Jnana Flux | C10: 6 | D10: 7 | E10: 7 | F10: 7 | G10: 10 | H10: =IF(COUNTA(C10:G10)=5,(0.1*C10+0.25*D10+0.3*E10+0.25*F10+0.1*G10),"") -> 7.2 | I10: Associate Information Hub: Good storytelling and presentation. Peoplesoft - source of truth. Lockaboo bot. Nice visual org chart. Knowledge base, web and teams app. Email based search only.
A11: 7 | B11: Locktonauts | C11: 8 | D11: 7 | E11: 9 | F11: 8 | G11: 9 | H11: =IF(COUNTA(C11:G11)=5,(0.1*C11+0.25*D11+0.3*E11+0.25*F11+0.1*G11),"") -> 8.15 | I11: Reccon/; Nagaraju - Invoice reconciliation. Doc intelligence. Good understanding of business problem. Smart review from AI analysis. Very cool web app. Brian - is this a smarter accounting view? Venk, Sakthi. Document and peoplesoft billing data.
A12: 8 | B12: Lockton AIvengers | C12: 6 | D12: 7 | E12: 8 | F12: 8 | G12: 7 | H12: =IF(COUNTA(C12:G12)=5,(0.1*C12+0.25*D12+0.3*E12+0.25*F12+0.1*G12),"") -> 7.45 | I12: Mohan, Arokiya, Prashant: Insurance Market intelligence: Chat input of files - sends email via outlook. Future: transcript is uploaded in Sharepoint - trigger the report generation. Extracts key focus points and then allows user to change the input before generating.
A13: 9 | B13: Hack & LOCK | C13: 6 | D13: 6 | E13: 7 | F13: 7 | G13: 7 | H13: =IF(COUNTA(C13:G13)=5,(0.1*C13+0.25*D13+0.3*E13+0.25*F13+0.1*G13),"") -> 6.65 | I13: Receptionist Lookup Modernizer: Modern web app with good UI. Send a message vs using status. Confidential note. Ahent based real time info -
A14: 10 | B14: PO 360 | C14: 6 | D14: 6 | E14: 8 | F14: 7 | G14: 6 | H14: =IF(COUNTA(C14:G14)=5,(0.1*C14+0.25*D14+0.3*E14+0.25*F14+0.1*G14),"") -> 6.85 | I14: POs for Office/Facilities: Magesh - funny role play. Full featured end to end power auotmate workflow. Invoice trigger. Store invoices with extracted metadata. Powerbi data set. IT & Transformation - good finish.
A15: 11 | B15: Lockton Legends | C15: 7 | D15: 7 | E15: 8 | F15: 8 | G15: 7 | H15: =IF(COUNTA(C15:G15)=5,(0.1*C15+0.25*D15+0.3*E15+0.25*F15+0.1*G15),"") -> 7.55 | I15: Sushma: Accounting View Agent. self service accounting. Inefficiencies in invoice status. Copilot & Mulesoft. Really fast response. Automated ticket creation. Good understanding of time efficiencies. Scope can be for more use cases. (Apalla, Uday...)
A16: 12 | B16: Ticket Hunters | C16: 6 | D16: 7 | E16: 7 | F16: 8 | G16: 7 | H16: =IF(COUNTA(C16:G16)=5,(0.1*C16+0.25*D16+0.3*E16+0.25*F16+0.1*G16),"") -> 7.15 | I16: B-Buddy. Smart budget forecasting: did homework to get understanding. Canvas with notes from leaders. Proactive Email alerts. Chatbot with historical data. Trend analysis by vendor data. PowerBI.
A17: 13 | B17: CloudMesh | C17: 5 | D17: 6 | E17: 5 | F17: 5 | G17: 6 | H17: =IF(COUNTA(C17:G17)=5,(0.1*C17+0.25*D17+0.3*E17+0.25*F17+0.1*G17),"") -> 5.35 | I17: ACH Verification: Swaroop. Centralized ACH portal. LIA - Lockton Intgel Asst. Vendor ACH info. Workflow. Web chatbot.

Sheet Molly
A1: 🏆 GAS 2026 HACKATHON - MOLLY BERNDT
A2: Score each criterion 1-10 (10 = Excellent). Weighted Total auto-calculates.
A3: WEIGHTAGE → | C3: 10% | D3: 25% | E3: 30% | F3: 25% | G3: 10%
A4: # | B4: Team | C4: Problem (10%) | D4: Innovation (25%) | E4: Technical (30%) | F4: Business (25%) | G4: Presentation (10%) | H4: Weighted Total | I4: Quick Notes
A5: 1 | B5: Lockton Govern-Lens | C5: 7 | D5: 6 | E5: 7 | F5: 6 | G5: 7 | H5: =IF(COUNTA(C5:G5)=5,(0.1*C5+0.25*D5+0.3*E5+0.25*F5+0.1*G5),"") -> 6.5 | I5: description: created a budget powerBI, an agent that can help forecast various stages of a budget and a vendor tracking form
A6: 2 | B6: Lockton Tech Squad | C6: 6 | D6: 7 | E6: 7 | F6: 6 | G6: 7 | H6: =IF(COUNTA(C6:G6)=5,(0.1*C6+0.25*D6+0.3*E6+0.25*F6+0.1*G6),"") -> 6.65 | I6: People Hub - starts with view of associates, Chatbot - to ask for details on a person. Part missed that we want to do away with associate directory
A7: 3 | B7: The Sentinels | C7: 9 | D7: 8 | E7: 8 | F7: 8 | G7: 10 | H7: =IF(COUNTA(C7:G7)=5,(0.1*C7+0.25*D7+0.3*E7+0.25*F7+0.1*G7),"") -> 8.3 | I7: Central invoice tracker/accelerator - great enthusiastic presentation
A8: 4 | B8: Lockathon | C8: 6 | D8: 8 | E8: 8 | F8: 5 | G8: 8 | H8: =IF(COUNTA(C8:G8)=5,(0.1*C8+0.25*D8+0.3*E8+0.25*F8+0.1*G8),"") -> 7.05 | I8: IT budgeting/monitoring/forecasting - had more AI functionality ,but as a user, I was confused - less straight forward
A9: 5 | B9: Neural Ninjas | C9: 2 | D9: 4 | E9: 6 | F9: 3 | G9: 5 | H9: =IF(COUNTA(C9:G9)=5,(0.1*C9+0.25*D9+0.3*E9+0.25*F9+0.1*G9),"") -> 4.25 | I9: Associate Rolodex - the main issue is you have to know empl id and it provided access to systems vs info about the users
A10: 6 | B10: Jnana Flux | C10: 7 | D10: 6 | E10: 7 | F10: 8 | G10: 9 | H10: =IF(COUNTA(C10:G10)=5,(0.1*C10+0.25*D10+0.3*E10+0.25*F10+0.1*G10),"") -> 7.2 | I10: Associate Information Hub - where jacob. This one had org chart and understood the problem the most
A11: 7 | B11: Locktonauts | C11: 2 | D11: 7 | E11: 6 | F11: 7 | G11: 8 | H11: =IF(COUNTA(C11:G11)=5,(0.1*C11+0.25*D11+0.3*E11+0.25*F11+0.1*G11),"") -> 6.3 | I11: I am not sure if the description of the project led in this direction but AV is an associate platform vs. an accounting user.
A12: 8 | B12: Lockton AIvengers | C12: 9 | D12: 7 | E12: 6 | F12: 8 | G12: 8 | H12: =IF(COUNTA(C12:G12)=5,(0.1*C12+0.25*D12+0.3*E12+0.25*F12+0.1*G12),"") -> 7.25 | I12: market intelligence
A13: 9 | B13: Hack & LOCK | C13: 7 | D13: 6 | E13: 5 | F13: 7 | G13: 7 | H13: =IF(COUNTA(C13:G13)=5,(0.1*C13+0.25*D13+0.3*E13+0.25*F13+0.1*G13),"") -> 6.15 | I13: Receptionist Lookup replacement - good UI, but not sure how AI email will help.
A14: 10 | B14: PO 360 | C14: 8 | D14: 6 | E14: 6 | F14: 7 | G14: 8 | H14: =IF(COUNTA(C14:G14)=5,(0.1*C14+0.25*D14+0.3*E14+0.25*F14+0.1*G14),"") -> 6.65 | I14: Purchase Order for office/facilities - the problem is solved well - had the team all talk for the cartoon.
A15: 11 | B15: Lockton Legends | C15: 6 | D15: 7 | E15: 6 | F15: 7 | G15: 7 | H15: =IF(COUNTA(C15:G15)=5,(0.1*C15+0.25*D15+0.3*E15+0.25*F15+0.1*G15),"") -> 6.6 | I15: Accounting helpdesk questions via chatbot
A16: 12 | B16: Ticket Hunters | C16: 6 | D16: 8 | E16: 8 | F16: 8 | G16: 7 | H16: =IF(COUNTA(C16:G16)=5,(0.1*C16+0.25*D16+0.3*E16+0.25*F16+0.1*G16),"") -> 7.7 | I16: B Buddy - budget tracker
A17: 13 | B17: CloudMesh | C17: 6 | D17: 6 | E17: 5 | F17: 7 | G17: 7 | H17: =IF(COUNTA(C17:G17)=5,(0.1*C17+0.25*D17+0.3*E17+0.25*F17+0.1*G17),"") -> 6.05 | I17: ACH Verification automation to prevent fraud for vendor payments from IT

Sheet Jamie
A1: 🏆 GAS 2026 HACKATHON - JAMIE SHAW
A2: Score each criterion 1-10 (10 = Excellent). Weighted Total auto-calculates.
A3: WEIGHTAGE → | C3: 10% | D3: 25% | E3: 30% | F3: 25% | G3: 10%
A4: # | B4: Team | C4: Problem (10%) | D4: Innovation (25%) | E4: Technical (30%) | F4: Business (25%) | G4: Presentation (10%) | H4: Weighted Total | I4: Quick Notes
A5: 1 | B5: Lockton Govern-Lens | C5: 5 | D5: 5 | E5: 7 | F5: 5 | G5: 7 | H5: =IF(COUNTA(C5:G5)=5,(0.1*C5+0.25*D5+0.3*E5+0.25*F5+0.1*G5),"") -> 5.8 | I5: IT Budget - AI specific functionality unclear of what it provides that we don't have through Copilot today or Link (US)
A6: 2 | B6: Lockton Tech Squad | C6: 7 | D6: 5 | E6: 7 | F6: 5 | G6: 7 | H6: =IF(COUNTA(C6:G6)=5,(0.1*C6+0.25*D6+0.3*E6+0.25*F6+0.1*G6),"") -> 6 | I6: People Hub - AI functionality is dependent on people keeping GAD (or a new app?) updated with whereabouts and skills
A7: 3 | B7: The Sentinels | C7: 8 | D7: 8 | E7: 8 | F7: 8 | G7: 10 | H7: =IF(COUNTA(C7:G7)=5,(0.1*C7+0.25*D7+0.3*E7+0.25*F7+0.1*G7),"") -> 8.2 | I7: IT Invoice - This is an improvement to what we have today and is worth exploring more, at least the automation, which can be set up through Power Automate but assuming AI will be or could be used'
A8: 4 | B8: Lockathon | C8: 8 | D8: 8 | E8: 8 | F8: 10 | G8: 9 | H8: =IF(COUNTA(C8:G8)=5,(0.1*C8+0.25*D8+0.3*E8+0.25*F8+0.1*G8),"") -> 8.6 | I8: IT Budget - This had more AI functionality (agendtic I think?) above and beyond what we have today
A9: 5 | B9: Neural Ninjas | C9: 2 | D9: 3 | E9: 4 | F9: 2 | G9: 5 | H9: =IF(COUNTA(C9:G9)=5,(0.1*C9+0.25*D9+0.3*E9+0.25*F9+0.1*G9),"") -> 3.15 | I9: Roladex - It relies on knowing EMPL ID (which is the problem) or email (you have to know) and it will tell you if they have access to a system (?)
A10: 6 | B10: Jnana Flux | C10: 5 | D10: 4 | E10: 5 | F10: 5 | G10: 7 | H10: =IF(COUNTA(C10:G10)=5,(0.1*C10+0.25*D10+0.3*E10+0.25*F10+0.1*G10),"") -> 4.95 | I10: Roladex - innovation and capabilities felt like a lateral compared to today but UI was nicer
A11: 7 | B11: Locktonauts | C11: 2 | D11: 4 | E11: 6 | F11: 2 | G11: 8 | H11: =IF(COUNTA(C11:G11)=5,(0.1*C11+0.25*D11+0.3*E11+0.25*F11+0.1*G11),"") -> 4.3 | I11: Accounting View - Accounting View is not used for reconcilation so unsure of the problem being solved. It does help a problem, but not Accounting View.
A12: 8 | B12: Lockton AIvengers | C12: 8 | D12: 6 | E12: 7 | F12: 6 | G12: 7 | H12: =IF(COUNTA(C12:G12)=5,(0.1*C12+0.25*D12+0.3*E12+0.25*F12+0.1*G12),"") -> 6.6 | I12: Market Intelligence - the Teams audio was inconsistent
A13: 9 | B13: Hack & LOCK | C13: 7 | D13: 4 | E13: 5 | F13: 5 | G13: 8 | H13: =IF(COUNTA(C13:G13)=5,(0.1*C13+0.25*D13+0.3*E13+0.25*F13+0.1*G13),"") -> 5.25 | I13: Receptionist - followed directions provided but felt lateral in technology from today
A14: 10 | B14: PO 360 | C14: 6 | D14: 6 | E14: 6 | F14: 7 | G14: 6 | H14: =IF(COUNTA(C14:G14)=5,(0.1*C14+0.25*D14+0.3*E14+0.25*F14+0.1*G14),"") -> 6.25 | I14: Purchase Orders - unsure of the AI specific capabilties
A15: 11 | B15: Lockton Legends | C15: 6 | D15: 6 | E15: 7 | F15: 7 | G15: 7 | H15: =IF(COUNTA(C15:G15)=5,(0.1*C15+0.25*D15+0.3*E15+0.25*F15+0.1*G15),"") -> 6.65 | I15: Accounting View - Unsure of what the use case was trying to accomplish but the solution would be good
A16: 12 | B16: Ticket Hunters | C16: 7 | D16: 6 | E16: 7 | F16: 6 | G16: 8 | H16: =IF(COUNTA(C16:G16)=5,(0.1*C16+0.25*D16+0.3*E16+0.25*F16+0.1*G16),"") -> 6.6 | I16: Budget
A17: 13 | B17: CloudMesh | C17: 7 | D17: 6 | E17: 6 | F17: 6 | G17: 7 | H17: =IF(COUNTA(C17:G17)=5,(0.1*C17+0.25*D17+0.3*E17+0.25*F17+0.1*G17),"") -> 6.2 | I17: ACH Verification

Sheet 📊 Summary
A1: 🏆 ALL JUDGES SCORES SUMMARY
A2: Weighted scores from all 4 judges with average calculation
A3: # | B3: Team | C3: Byron | D3: Karthik | E3: Molly | F3: Jamie | G3: AVERAGE
A4: 1 | B4: Lockton Govern-Lens | C4: =IF(Byron!H5<>"",Byron!H5,"") -> 5.65 | D4: =IF(Karthik!H5<>"",Karthik!H5,"") -> 7.25 | E4: =IF(Molly!H5<>"",Molly!H5,"") -> 6.5 | F4: =IF(Jamie!H5<>"",Jamie!H5,"") -> 5.8 | G4: =IFERROR(IF(COUNT(C4:F4)>0,AVERAGE(C4:F4),""),"") -> 6.3 | H4: trv | I4: n
A5: 2 | B5: Lockton Tech Squad | C5: =IF(Byron!H6<>"",Byron!H6,"") -> 5.75 | D5: =IF(Karthik!H6<>"",Karthik!H6,"") -> 7.7 | E5: =IF(Molly!H6<>"",Molly!H6,"") -> 6.65 | F5: =IF(Jamie!H6<>"",Jamie!H6,"") -> 6 | G5: =IFERROR(IF(COUNT(C5:F5)>0,AVERAGE(C5:F5),""),"") -> 6.525 | H5: trv
A6: 3 | B6: The Sentinels | C6: =IF(Byron!H7<>"",Byron!H7,"") -> 6.8 | D6: =IF(Karthik!H7<>"",Karthik!H7,"") -> 7.25 | E6: =IF(Molly!H7<>"",Molly!H7,"") -> 8.3 | F6: =IF(Jamie!H7<>"",Jamie!H7,"") -> 8.2 | G6: =IFERROR(IF(COUNT(C6:F6)>0,AVERAGE(C6:F6),""),"") -> 7.6375 | H6: trv | I6: 1
A7: 4 | B7: Lockathon | C7: =IF(Byron!H8<>"",Byron!H8,"") -> 6.5 | D7: =IF(Karthik!H8<>"",Karthik!H8,"") -> 7.45 | E7: =IF(Molly!H8<>"",Molly!H8,"") -> 7.05 | F7: =IF(Jamie!H8<>"",Jamie!H8,"") -> 8.6 | G7: =IFERROR(IF(COUNT(C7:F7)>0,AVERAGE(C7:F7),""),"") -> 7.4 | H7: chn | I7: 2
A8: 5 | B8: Neural Ninjas | C8: =IF(Byron!H9<>"",Byron!H9,"") -> 6.05 | D8: =IF(Karthik!H9<>"",Karthik!H9,"") -> 6.3 | E8: =IF(Molly!H9<>"",Molly!H9,"") -> 4.25 | F8: =IF(Jamie!H9<>"",Jamie!H9,"") -> 3.15 | G8: =IFERROR(IF(COUNT(C8:F8)>0,AVERAGE(C8:F8),""),"") -> 4.9375 | H8: trv | I8: n
A9: 6 | B9: Jnana Flux | C9: =IF(Byron!H10<>"",Byron!H10,"") -> 6.85 | D9: =IF(Karthik!H10<>"",Karthik!H10,"") -> 7.2 | E9: =IF(Molly!H10<>"",Molly!H10,"") -> 7.2 | F9: =IF(Jamie!H10<>"",Jamie!H10,"") -> 4.95 | G9: =IFERROR(IF(COUNT(C9:F9)>0,AVERAGE(C9:F9),""),"") -> 6.55 | H9: trv
A10: 7 | B10: Locktonauts | C10: =IF(Byron!H11<>"",Byron!H11,"") -> 6.95 | D10: =IF(Karthik!H11<>"",Karthik!H11,"") -> 8.15 | E10: =IF(Molly!H11<>"",Molly!H11,"") -> 6.3 | F10: =IF(Jamie!H11<>"",Jamie!H11,"") -> 4.3 | G10: =IFERROR(IF(COUNT(C10:F10)>0,AVERAGE(C10:F10),""),"") -> 6.425 | H10: chn
A11: 8 | B11: Lockton AIvengers | C11: =IF(Byron!H12<>"",Byron!H12,"") -> 6.7 | D11: =IF(Karthik!H12<>"",Karthik!H12,"") -> 7.45 | E11: =IF(Molly!H12<>"",Molly!H12,"") -> 7.25 | F11: =IF(Jamie!H12<>"",Jamie!H12,"") -> 6.6 | G11: =IFERROR(IF(COUNT(C11:F11)>0,AVERAGE(C11:F11),""),"") -> 7 | H11: chn
A12: 9 | B12: Hack & LOCK | C12: =IF(Byron!H13<>"",Byron!H13,"") -> 6.8 | D12: =IF(Karthik!H13<>"",Karthik!H13,"") -> 6.65 | E12: =IF(Molly!H13<>"",Molly!H13,"") -> 6.15 | F12: =IF(Jamie!H13<>"",Jamie!H13,"") -> 5.25 | G12: =IFERROR(IF(COUNT(C12:F12)>0,AVERAGE(C12:F12),""),"") -> 6.2125 | H12: trv
A13: 10 | B13: PO 360 | C13: =IF(Byron!H14<>"",Byron!H14,"") -> 6.95 | D13: =IF(Karthik!H14<>"",Karthik!H14,"") -> 6.85 | E13: =IF(Molly!H14<>"",Molly!H14,"") -> 6.65 | F13: =IF(Jamie!H14<>"",Jamie!H14,"") -> 6.25 | G13: =IFERROR(IF(COUNT(C13:F13)>0,AVERAGE(C13:F13),""),"") -> 6.675 | H13: chn
A14: 11 | B14: Lockton Legends | C14: =IF(Byron!H15<>"",Byron!H15,"") -> 7.3 | D14: =IF(Karthik!H15<>"",Karthik!H15,"") -> 7.55 | E14: =IF(Molly!H15<>"",Molly!H15,"") -> 6.6 | F14: =IF(Jamie!H15<>"",Jamie!H15,"") -> 6.65 | G14: =IFERROR(IF(COUNT(C14:F14)>0,AVERAGE(C14:F14),""),"") -> 7.025 | H14: chn
A15: 12 | B15: Ticket Hunters | C15: =IF(Byron!H16<>"",Byron!H16,"") -> 6.95 | D15: =IF(Karthik!H16<>"",Karthik!H16,"") -> 7.15 | E15: =IF(Molly!H16<>"",Molly!H16,"") -> 7.7 | F15: =IF(Jamie!H16<>"",Jamie!H16,"") -> 6.6 | G15: =IFERROR(IF(COUNT(C15:F15)>0,AVERAGE(C15:F15),""),"") -> 7.1 | H15: trv | I15: 3
A16: 13 | B16: CloudMesh | C16: =IF(Byron!H17<>"",Byron!H17,"") -> 6.4 | D16: =IF(Karthik!H17<>"",Karthik!H17,"") -> 5.35 | E16: =IF(Molly!H17<>"",Molly!H17,"") -> 6.05 | F16: =IF(Jamie!H17<>"",Jamie!H17,"") -> 6.2 | G16: =IFERROR(IF(COUNT(C16:F16)>0,AVERAGE(C16:F16),""),"") -> 6 | H16: trv | I16: n

Sheet 🏅 Rankings
A1: 🏅 FINAL RANKINGS - TOP 3 WINNERS
A2: Sorted by average score (highest to lowest)
A3: Rank | B3: Team | C3: Avg Score | D3: Medal
A4: 1 | B4: =IFERROR(INDEX('📊 Summary'!$B$4:$B$16,MATCH(LARGE('📊 Summary'!$G$4:$G$16,1),'📊 Summary'!$G$4:$G$16,0)),"") -> The Sentinels | C4: =IFERROR(LARGE('📊 Summary'!$G$4:$G$16,1),"") -> 7.6375 | D4: 🥇 GOLD
A5: 2 | B5: =IFERROR(INDEX('📊 Summary'!$B$4:$B$16,MATCH(LARGE('📊 Summary'!$G$4:$G$16,2),'📊 Summary'!$G$4:$G$16,0)),"") -> Lockathon | C5: =IFERROR(LARGE('📊 Summary'!$G$4:$G$16,2),"") -> 7.4 | D5: 🥈 SILVER
A6: 3 | B6: =IFERROR(INDEX('📊 Summary'!$B$4:$B$16,MATCH(LARGE('📊 Summary'!$G$4:$G$16,3),'📊 Summary'!$G$4:$G$16,0)),"") -> Ticket Hunters | C6: =IFERROR(LARGE('📊 Summary'!$G$4:$G$16,3),"") -> 7.1 | D6: 🥉 BRONZE
A7: 4 | B7: =IFERROR(INDEX('📊 Summary'!$B$4:$B$16,MATCH(LARGE('📊 Summary'!$G$4:$G$16,4),'📊 Summary'!$G$4:$G$16,0)),"") -> Lockton Legends | C7: =IFERROR(LARGE('📊 Summary'!$G$4:$G$16,4),"") -> 7.025
A8: 5 | B8: =IFERROR(INDEX('📊 Summary'!$B$4:$B$16,MATCH(LARGE('📊 Summary'!$G$4:$G$16,5),'📊 Summary'!$G$4:$G$16,0)),"") -> Lockton AIvengers | C8: =IFERROR(LARGE('📊 Summary'!$G$4:$G$16,5),"") -> 7
A9: 6 | B9: =IFERROR(INDEX('📊 Summary'!$B$4:$B$16,MATCH(LARGE('📊 Summary'!$G$4:$G$16,6),'📊 Summary'!$G$4:$G$16,0)),"") -> PO 360 | C9: =IFERROR(LARGE('📊 Summary'!$G$4:$G$16,6),"") -> 6.675
A10: 7 | B10: =IFERROR(INDEX('📊 Summary'!$B$4:$B$16,MATCH(LARGE('📊 Summary'!$G$4:$G$16,7),'📊 Summary'!$G$4:$G$16,0)),"") -> Jnana Flux | C10: =IFERROR(LARGE('📊 Summary'!$G$4:$G$16,7),"") -> 6.55
A11: 8 | B11: =IFERROR(INDEX('📊 Summary'!$B$4:$B$16,MATCH(LARGE('📊 Summary'!$G$4:$G$16,8),'📊 Summary'!$G$4:$G$16,0)),"") -> Lockton Tech Squad | C11: =IFERROR(LARGE('📊 Summary'!$G$4:$G$16,8),"") -> 6.525
A12: 9 | B12: =IFERROR(INDEX('📊 Summary'!$B$4:$B$16,MATCH(LARGE('📊 Summary'!$G$4:$G$16,9),'📊 Summary'!$G$4:$G$16,0)),"") -> Locktonauts | C12: =IFERROR(LARGE('📊 Summary'!$G$4:$G$16,9),"") -> 6.425
A13: 10 | B13: =IFERROR(INDEX('📊 Summary'!$B$4:$B$16,MATCH(LARGE('📊 Summary'!$G$4:$G$16,10),'📊 Summary'!$G$4:$G$16,0)),"") -> Lockton Govern-Lens | C13: =IFERROR(LARGE('📊 Summary'!$G$4:$G$16,10),"") -> 6.3
A14: 11 | B14: =IFERROR(INDEX('📊 Summary'!$B$4:$B$16,MATCH(LARGE('📊 Summary'!$G$4:$G$16,11),'📊 Summary'!$G$4:$G$16,0)),"") -> Hack & LOCK | C14: =IFERROR(LARGE('📊 Summary'!$G$4:$G$16,11),"") -> 6.2125
A15: 12 | B15: =IFERROR(INDEX('📊 Summary'!$B$4:$B$16,MATCH(LARGE('📊 Summary'!$G$4:$G$16,12),'📊 Summary'!$G$4:$G$16,0)),"") -> CloudMesh | C15: =IFERROR(LARGE('📊 Summary'!$G$4:$G$16,12),"") -> 6
A16: 13 | B16: =IFERROR(INDEX('📊 Summary'!$B$4:$B$16,MATCH(LARGE('📊 Summary'!$G$4:$G$16,13),'📊 Summary'!$G$4:$G$16,0)),"") -> Neural Ninjas | C16: =IFERROR(LARGE('📊 Summary'!$G$4:$G$16,13),"") -> 4.9375
